{
	"version": "https://jsonfeed.org/version/1.1",
	"title": "YJD𝕏",
	"language": "en",
	"home_page_url": "https://yjdx.netlify.app/yjdx/",
	"feed_url": "https://yjdx.netlify.app/yjdx/feed/feed.json",
	"description": "The homogenous customised blog of Yeshua D&#39;Costa.",
	"author": {
		"name": "Yeshua D&#39;Costa",
		"url": "https://yjdx.netlify.app/"
	},
	"items": [
		{
			"id": "https://yjdx.netlify.app/yjdx/blog/prayer/",
			"url": "https://yjdx.netlify.app/yjdx/blog/prayer/",
			"title": "Poem On Prayer",
			"content_html": "<h3 id=\"poem-on-prayer\" tabindex=\"-1\">Poem On Prayer <a class=\"header-anchor\" href=\"https://yjdx.netlify.app/yjdx/blog/prayer/\">#</a></h3>\n<p><strong>Prayer</strong>, What a <em>beautiful</em> thing<br>\nRaid the <strong>devil</strong>, <em>victory</em> you shall bring;<br>\n<em>Abandon</em> your <strong>wordly addictions</strong><br>\n<em>Yearn</em> for <strong>God</strong>,<br>\nHe will <em>eradicate</em> your <strong>afflictions</strong>;<br>\n<em>Raise</em> up your problems,<br>\n<em><strong>Prayer helps with that</strong></em><br>\n<strong>Faithfulness</strong>, it <em>instills</em> in you,<br>\nCertainly <strong>not</strong> the spirit of a <em>brat.</em></p>\n<p>~Yeshua D'Costa</p>\n",
			"date_published": "2023-12-04T00:00:00Z"
		}
		,
		{
			"id": "https://yjdx.netlify.app/yjdx/blog/collatzConjecture/",
			"url": "https://yjdx.netlify.app/yjdx/blog/collatzConjecture/",
			"title": "The Impossible Conjecture",
			"content_html": "<h3 id=\"introduction\" tabindex=\"-1\">Introduction <a class=\"header-anchor\" href=\"https://yjdx.netlify.app/yjdx/blog/collatzConjecture/\">#</a></h3>\n<p>The Collatz Conjecture is an unsolved problem in mathematics. This conjecture is named after the mathematician Lothar Collatz, who introduced the idea in 1937. The conjecture also known as Syrucuse conjecture or problem.</p>\n<p><em>Take any positive integer n. If n is even then divide it by 2, else do &quot;triple plus one&quot; and get 3n+1. The conjecture is that for all numbers, this process converges to <strong>one</strong>.</em></p>\n<blockquote>\n<p>Paul Erdős said about the Collatz conjecture, &quot;Mathematics may not be ready for such problems.&quot;</p>\n</blockquote>\n<blockquote>\n<p>Jeffrey Lagarias stated that the Collatz conjecture &quot;is an extraordinarily difficult problem, completely out of reach of present day mathematics.&quot;</p>\n</blockquote>\n<p><strong>Implementation Of The Collatz Conjecture in C++</strong></p>\n<pre class=\"language-c\" tabindex=\"0\"><code class=\"language-c\"><span class=\"token macro property\"><span class=\"token directive-hash\">#</span><span class=\"token directive keyword\">include</span> <span class=\"token string\">&lt;iostream></span></span>\n\nusing namespace std<span class=\"token punctuation\">;</span>\n\n<span class=\"token keyword\">int</span> <span class=\"token function\">main</span> <span class=\"token punctuation\">(</span><span class=\"token punctuation\">)</span><span class=\"token punctuation\">{</span>\n  <span class=\"token keyword\">int</span> numeral<span class=\"token punctuation\">{</span><span class=\"token number\">0</span><span class=\"token punctuation\">}</span><span class=\"token punctuation\">;</span>\n\n\tcout <span class=\"token operator\">&lt;&lt;</span> <span class=\"token string\">\"Enter the Numeral: \"</span><span class=\"token punctuation\">;</span>\n\tcin <span class=\"token operator\">>></span> numeral<span class=\"token punctuation\">;</span>\n\n    <span class=\"token keyword\">int</span> MAX_ITERATIONS<span class=\"token punctuation\">{</span><span class=\"token number\">0</span><span class=\"token punctuation\">}</span><span class=\"token punctuation\">;</span>\n    <span class=\"token keyword\">int</span> count<span class=\"token punctuation\">{</span><span class=\"token number\">0</span><span class=\"token punctuation\">}</span><span class=\"token punctuation\">;</span>\n\n    cout <span class=\"token operator\">&lt;&lt;</span> <span class=\"token string\">\"Enter the number of iterations of the sequence: \"</span><span class=\"token punctuation\">;</span>\n    cin <span class=\"token operator\">>></span> MAX_ITERATIONS<span class=\"token punctuation\">;</span>\n\n    <span class=\"token keyword\">while</span> <span class=\"token punctuation\">(</span>count<span class=\"token operator\">&lt;=</span>MAX_ITERATIONS<span class=\"token punctuation\">)</span><span class=\"token punctuation\">{</span>\n        <span class=\"token keyword\">if</span> <span class=\"token punctuation\">(</span>numeral<span class=\"token operator\">%</span><span class=\"token number\">2</span> <span class=\"token operator\">==</span> <span class=\"token number\">0</span><span class=\"token punctuation\">)</span><span class=\"token punctuation\">{</span>\n            <span class=\"token comment\">// If the numeral is even, divide it by 2</span>\n            numeral <span class=\"token operator\">=</span> <span class=\"token punctuation\">(</span>numeral<span class=\"token operator\">/</span><span class=\"token number\">2</span><span class=\"token punctuation\">)</span><span class=\"token punctuation\">;</span>\n            cout <span class=\"token operator\">&lt;&lt;</span> <span class=\"token string\">\"/2: \"</span> <span class=\"token operator\">&lt;&lt;</span> numeral <span class=\"token operator\">&lt;&lt;</span> endl<span class=\"token punctuation\">;</span>\n        <span class=\"token punctuation\">}</span>\n        <span class=\"token keyword\">else</span> <span class=\"token keyword\">if</span> <span class=\"token punctuation\">(</span>numeral<span class=\"token operator\">%</span><span class=\"token number\">2</span><span class=\"token operator\">!=</span><span class=\"token number\">0</span><span class=\"token punctuation\">)</span><span class=\"token punctuation\">{</span>\n            <span class=\"token comment\">// If the numeral is odd, multiply it by 3 and add 1</span>\n            numeral <span class=\"token operator\">=</span> <span class=\"token punctuation\">(</span>numeral<span class=\"token operator\">*</span><span class=\"token number\">3</span><span class=\"token punctuation\">)</span><span class=\"token operator\">+</span><span class=\"token number\">1</span><span class=\"token punctuation\">;</span>\n            cout <span class=\"token operator\">&lt;&lt;</span> <span class=\"token string\">\"3x+1: \"</span> <span class=\"token operator\">&lt;&lt;</span> numeral <span class=\"token operator\">&lt;&lt;</span> endl<span class=\"token punctuation\">;</span>\n        <span class=\"token punctuation\">}</span>\n\n        <span class=\"token comment\">// The following code restricts the number of repetitions of the sequence `4, 2, 1`</span>\n        <span class=\"token keyword\">if</span> <span class=\"token punctuation\">(</span>numeral <span class=\"token operator\">==</span> <span class=\"token number\">1</span><span class=\"token punctuation\">)</span>\n            <span class=\"token operator\">++</span>count<span class=\"token punctuation\">;</span>\n    <span class=\"token punctuation\">}</span>\n\n    cout <span class=\"token operator\">&lt;&lt;</span> <span class=\"token string\">\"The sequence `4, 2, 1` has been repeated \"</span> <span class=\"token operator\">&lt;&lt;</span> MAX_ITERATIONS <span class=\"token operator\">&lt;&lt;</span> <span class=\"token string\">\" times!\"</span><span class=\"token punctuation\">;</span>\n    <span class=\"token keyword\">return</span> <span class=\"token number\">0</span><span class=\"token punctuation\">;</span>\n<span class=\"token punctuation\">}</span></code></pre>\n<p>The constant <code>MAX_ITERATIONS</code> controls the maximum number of times, the sequence <code>4, 2, 1</code> is repeated while the variable <code>count</code> stores the number of occurences of the number <code>1</code></p>\n<p>If the number is <em>even</em>, it is divided by <code>2</code>, its divisibility by <code>2</code> is proven by <code>numeral%2</code>, which in this case, should be equal to zero.</p>\n<p>If the number is <em>odd</em>, it is multiplied by <code>3</code> and '1' is added to the product, its divisibility by <code>2</code> in this case <code>numeral%2</code>, should not be equal to zero and should provide the remainder of the number on division by <code>2</code></p>\n<p><strong>Output of the C++ Code</strong></p>\n<p>For the following example, the number <code>10</code> has been used</p>\n<pre class=\"language-bash\" tabindex=\"0\"><code class=\"language-bash\">Enter the Numeral: <span class=\"token number\">10</span>\nEnter the number of iterations of the sequence: <span class=\"token number\">3</span>\n/2: <span class=\"token number\">5.0</span>\n3x+1: <span class=\"token number\">16.0</span>\n/2: <span class=\"token number\">8.0</span>\n/2: <span class=\"token number\">4.0</span>\n/2: <span class=\"token number\">2.0</span>\n/2: <span class=\"token number\">1.0</span>\n3x+1: <span class=\"token number\">4.0</span>\n/2: <span class=\"token number\">2.0</span>\n/2: <span class=\"token number\">1.0</span>\n3x+1: <span class=\"token number\">4.0</span>\n/2: <span class=\"token number\">2.0</span>\n/2: <span class=\"token number\">1.0</span>\n3x+1: <span class=\"token number\">4.0</span>\n/2: <span class=\"token number\">2.0</span>\n/2: <span class=\"token number\">1.0</span>\nThe sequence <span class=\"token variable\"><span class=\"token variable\">`</span><span class=\"token number\">4</span>, <span class=\"token number\">2</span>, <span class=\"token number\">1</span><span class=\"token variable\">`</span></span> has been repeated <span class=\"token number\">3</span> times.</code></pre>\n",
			"date_published": "2023-10-29T00:00:00Z"
		}
		
	]
}
